d2s/__init__.py
d2s/__main__.py
d2s/generate_metadata.py
d2s/generate_shacl.py
d2s/graph_builder.py
d2s/process_datasets.py
d2s/sparql_operations.py
d2s/utils.py
d2s/queries/bio2rdf/1_1_count_namespaces.rq
d2s/queries/hcls/1_1_count_triples.rq
d2s/queries/hcls/1_2_count_entities.rq
d2s/queries/hcls/1_3_count_distinctSubjects.rq
d2s/queries/hcls/1_4_count_distinctProperties.rq
d2s/queries/hcls/1_5_count_distinctObjects.rq
d2s/queries/hcls/1_6_count_distinctClasses.rq
d2s/queries/hcls/1_7_count_distinctLiterals.rq
d2s/queries/hcls/2_2_count_instances_per_classes.rq
d2s/queries/hcls/2_3_count_instances_linked_to_property.rq
d2s/queries/hcls/2_4_count_objects_linked_to_property.rq
d2s/queries/hcls/2_5_count_literal_linked_to_property.rq
d2s/queries/hcls/2_6_count_subject_object_links.rq
d2s/templates/process-dataset.yml
d2s/templates/dataset/dataset-yourdataset.jsonld
d2s/templates/dataset/mapping.yarrr.yml
d2s/templates/dataset/prepare.sh
d2s/templates/project/LICENSE
d2s/templates/project/README.md
d2s/templates/project/d2s.yml
d2s/templates/project/requirements.txt
tests/__init__.py
tests/test_d2s.py
d2s-0.3.3.dist-info/LICENSE
d2s-0.3.3.dist-info/METADATA
d2s-0.3.3.dist-info/WHEEL
d2s-0.3.3.dist-info/entry_points.txt
d2s-0.3.3.dist-info/top_level.txt
d2s-0.3.3.dist-info/RECORD
