Metadata-Version: 2.1
Name: d2s
Version: 0.3.3
Summary: A Command Line Interface to orchestrate the integration of heterogenous data and the deployment of services consuming the integrated data. See https://d2s.semanticscience.org
Home-page: https://github.com/MaastrichtU-IDS/d2s-cli
Author: Vincent Emonet
Author-email: vincent.emonet@gmail.com
License: MIT License
Project-URL: Issues, https://github.com/MaastrichtU-IDS/d2s-cli/issues
Project-URL: Source Code, https://github.com/MaastrichtU-IDS/d2s-cli
Project-URL: CI, https://github.com/MaastrichtU-IDS/d2s-cli/actions
Project-URL: Releases, https://github.com/MaastrichtU-IDS/d2s-cli/releases
Platform: UNKNOWN
Classifier: License :: OSI Approved :: MIT License
Classifier: Programming Language :: Python :: 3
Classifier: Programming Language :: Python :: 3.7
Classifier: Programming Language :: Python :: 3.8
Classifier: Programming Language :: Python :: 3.9
Requires-Dist: Click (<8.0.0,>=7.0.0)
Requires-Dist: rdflib (>=6.1.1)
Requires-Dist: SPARQLWrapper
Requires-Dist: python-dotenv
Requires-Dist: GitPython
Requires-Dist: requests
Requires-Dist: PyYAML
Requires-Dist: python-dateutil
Requires-Dist: pandas
